odoo/addons/sequence_python/README.rst
odoo/addons/sequence_python/__init__.py
odoo/addons/sequence_python/__manifest__.py
odoo/addons/sequence_python/i18n/ca.po
odoo/addons/sequence_python/i18n/es_AR.po
odoo/addons/sequence_python/i18n/it.po
odoo/addons/sequence_python/i18n/sequence_python.pot
odoo/addons/sequence_python/models/__init__.py
odoo/addons/sequence_python/models/ir_sequence.py
odoo/addons/sequence_python/readme/CONTRIBUTORS.md
odoo/addons/sequence_python/readme/DESCRIPTION.md
odoo/addons/sequence_python/readme/USAGE.md
odoo/addons/sequence_python/static/description/icon.png
odoo/addons/sequence_python/static/description/index.html
odoo/addons/sequence_python/tests/__init__.py
odoo/addons/sequence_python/tests/test_ir_sequence.py
odoo/addons/sequence_python/views/ir_sequence.xml
odoo_addon_sequence_python-18.0.1.0.0.2.dist-info/METADATA
odoo_addon_sequence_python-18.0.1.0.0.2.dist-info/WHEEL
odoo_addon_sequence_python-18.0.1.0.0.2.dist-info/top_level.txt
odoo_addon_sequence_python-18.0.1.0.0.2.dist-info/RECORD
